{
  "code": 0,
  "data": {
    "records": [
      {
        "_id": "661fffbc17071f48448b1fc0",
        "caption": "布鲁诺",
        "configId": 144237,
        "createdAt": 1713373116378,
        "createdUser": "rubickguo",
        "data": {
          "_object": 2684183,
          "desc": "In teamfights, start with Bruno's 1st Skill to get a Powerball and try to get in as much damage as possible. Look for enemies that are close together to use his Ultimate on, then use his Basic Attacks and 2nd Skill to secure the kill or retreat from danger.",
          "hero_id": 12,
          "skill_id": [
            {
              "_createdAt": 1730960697288,
              "_id": "672c5d399d856a6db37d93a1",
              "_updatedAt": 1758787887535,
              "data": {
                "skillicon": "https://akmweb.youngjoygame.com/web/svnres/img/mlbb/homepage/100_65a5b817dc5f53e082caa8c1def5a9ef.png",
                "skillid": 1210
              },
              "id": 109745,
              "sourceId": 2674712
            },
            {
              "_createdAt": 1730960697288,
              "_id": "672c5d399d856a6db37d939e",
              "_updatedAt": 1758787887535,
              "data": {
                "skillicon": "https://akmweb.youngjoygame.com/web/svnres/img/mlbb/homepage_92/100_f98d2e98eaebfb31c6c5101cf1c3201a.png",
                "skillid": 1200
              },
              "id": 109742,
              "sourceId": 2674712
            },
            {
              "_createdAt": 1730960697288,
              "_id": "672c5d399d856a6db37d93a3",
              "_updatedAt": 1758787887535,
              "data": {
                "skillicon": "https://akmweb.youngjoygame.com/web/svnres/img/mlbb/homepage/100_0d4558404b2096ecbce8394de5ced030.png",
                "skillid": 1230
              },
              "id": 109747,
              "sourceId": 2674712
            },
            {
              "_createdAt": 1730960697288,
              "_id": "672c5d399d856a6db37d939e",
              "_updatedAt": 1758787887535,
              "data": {
                "skillicon": "https://akmweb.youngjoygame.com/web/svnres/img/mlbb/homepage_92/100_f98d2e98eaebfb31c6c5101cf1c3201a.png",
                "skillid": 1200
              },
              "id": 109742,
              "sourceId": 2674712
            },
            {
              "_createdAt": 1730960697288,
              "_id": "672c5d399d856a6db37d93a0",
              "_updatedAt": 1758787887535,
              "data": {
                "skillicon": "https://akmweb.youngjoygame.com/web/svnres/img/mlbb/homepage/100_02cfbd7b97612b6aedb46d84a3186ce4.png",
                "skillid": 1220
              },
              "id": 109744,
              "sourceId": 2674712
            },
            {
              "_createdAt": 1730960697288,
              "_id": "672c5d399d856a6db37d939e",
              "_updatedAt": 1758787887535,
              "data": {
                "skillicon": "https://akmweb.youngjoygame.com/web/svnres/img/mlbb/homepage_92/100_f98d2e98eaebfb31c6c5101cf1c3201a.png",
                "skillid": 1200
              },
              "id": 109742,
              "sourceId": 2674712
            }
          ],
          "title": "TEAMFIGHT COMBOS"
        },
        "dynamic": null,
        "id": 2694876,
        "linkId": [
          2684183
        ],
        "sort": 0,
        "updatedAt": 1713930266932,
        "updatedUser": "v_hwu"
      },
      {
        "_id": "661fffbc17071f48448b1fbc",
        "caption": "布鲁诺",
        "configId": 144237,
        "createdAt": 1713373116368,
        "createdUser": "rubickguo",
        "data": {
          "_object": 2684183,
          "desc": "In the laning phase, use Bruno's 1st Skill to get a Powerball, and start attacking the enemy while picking up the ball. When the target is low, stun them with his 2nd Skill and finish them off with Basic Attacks.",
          "hero_id": 12,
          "skill_id": [
            {
              "_createdAt": 1730960697288,
              "_id": "672c5d399d856a6db37d93a1",
              "_updatedAt": 1758787887535,
              "data": {
                "skillicon": "https://akmweb.youngjoygame.com/web/svnres/img/mlbb/homepage/100_65a5b817dc5f53e082caa8c1def5a9ef.png",
                "skillid": 1210
              },
              "id": 109745,
              "sourceId": 2674712
            },
            {
              "_createdAt": 1730960697288,
              "_id": "672c5d399d856a6db37d939e",
              "_updatedAt": 1758787887535,
              "data": {
                "skillicon": "https://akmweb.youngjoygame.com/web/svnres/img/mlbb/homepage_92/100_f98d2e98eaebfb31c6c5101cf1c3201a.png",
                "skillid": 1200
              },
              "id": 109742,
              "sourceId": 2674712
            },
            {
              "_createdAt": 1730960697288,
              "_id": "672c5d399d856a6db37d93a0",
              "_updatedAt": 1758787887535,
              "data": {
                "skillicon": "https://akmweb.youngjoygame.com/web/svnres/img/mlbb/homepage/100_02cfbd7b97612b6aedb46d84a3186ce4.png",
                "skillid": 1220
              },
              "id": 109744,
              "sourceId": 2674712
            },
            {
              "_createdAt": 1730960697288,
              "_id": "672c5d399d856a6db37d939e",
              "_updatedAt": 1758787887535,
              "data": {
                "skillicon": "https://akmweb.youngjoygame.com/web/svnres/img/mlbb/homepage_92/100_f98d2e98eaebfb31c6c5101cf1c3201a.png",
                "skillid": 1200
              },
              "id": 109742,
              "sourceId": 2674712
            }
          ],
          "title": "LANING COMBOS"
        },
        "dynamic": null,
        "id": 2694875,
        "linkId": [
          2684183
        ],
        "sort": 0,
        "updatedAt": 1713373219995,
        "updatedUser": "rubickguo"
      }
    ],
    "total": 2
  },
  "message": "OK",
  "traceID": null
}