{
  "code": 0,
  "data": {
    "records": [
      {
        "_id": "662000c517071f48448b245c",
        "caption": "诺瓦利娅",
        "configId": 144237,
        "createdAt": 1713373381589,
        "createdUser": "rubickguo",
        "data": {
          "_object": 2684183,
          "desc": "In teamfights, use Novaria's Ultimate to gain vision of the battlefield, then summon an Astral Sphere with her 2nd Skill. After catching the Astral Sphere, launch it to damage the enemy and use her 1st Skill to thwart enemy heroes that try to get close.",
          "hero_id": 119,
          "skill_id": [
            {
              "_createdAt": 1730960697288,
              "_id": "672c5d399d856a6db37d95da",
              "_updatedAt": 1758787887535,
              "data": {
                "skillicon": "https://akmweb.youngjoygame.com/web/svnres/img/mlbb/homepage/100_76e8b6d3cb047f2b5f1a3d21469b40f6.png",
                "skillid": 11930
              },
              "id": 110314,
              "sourceId": 2674712
            },
            {
              "_createdAt": 1730960697288,
              "_id": "672c5d399d856a6db37d95d5",
              "_updatedAt": 1758787887535,
              "data": {
                "skillicon": "https://akmweb.youngjoygame.com/web/svnres/img/mlbb/homepage/100_18a74de4a5f949bac5b6d3a6d8a9180b.png",
                "skillid": 11920
              },
              "id": 110309,
              "sourceId": 2674712
            },
            {
              "_createdAt": 1730960697288,
              "_id": "672c5d399d856a6db37d95d5",
              "_updatedAt": 1758787887535,
              "data": {
                "skillicon": "https://akmweb.youngjoygame.com/web/svnres/img/mlbb/homepage/100_18a74de4a5f949bac5b6d3a6d8a9180b.png",
                "skillid": 11920
              },
              "id": 110309,
              "sourceId": 2674712
            },
            {
              "_createdAt": 1730960697288,
              "_id": "672c5d399d856a6db37d95d6",
              "_updatedAt": 1758787887535,
              "data": {
                "skillicon": "https://akmweb.youngjoygame.com/web/svnres/img/mlbb/homepage/100_276900dd1748403fba313aa10476e8f0.png",
                "skillid": 11910
              },
              "id": 110310,
              "sourceId": 2674712
            }
          ],
          "title": "TEAMFIGHT COMBOS"
        },
        "dynamic": null,
        "id": 2695070,
        "linkId": [
          2684183
        ],
        "sort": 0,
        "updatedAt": 1713373398175,
        "updatedUser": "rubickguo"
      },
      {
        "_id": "662000c517071f48448b2458",
        "caption": "诺瓦利娅",
        "configId": 144237,
        "createdAt": 1713373381579,
        "createdUser": "rubickguo",
        "data": {
          "_object": 2684183,
          "desc": "In the laning phase, initiate by using Novaria's 2nd Skill to gain extra Movement Speed and summon an Astral Sphere. Then, slow the enemy with her 1st Skill and use her 2nd Skill again to launch the Astral Sphere to deal damage.",
          "hero_id": 119,
          "skill_id": [
            {
              "_createdAt": 1730960697288,
              "_id": "672c5d399d856a6db37d95d5",
              "_updatedAt": 1758787887535,
              "data": {
                "skillicon": "https://akmweb.youngjoygame.com/web/svnres/img/mlbb/homepage/100_18a74de4a5f949bac5b6d3a6d8a9180b.png",
                "skillid": 11920
              },
              "id": 110309,
              "sourceId": 2674712
            },
            {
              "_createdAt": 1730960697288,
              "_id": "672c5d399d856a6db37d95d6",
              "_updatedAt": 1758787887535,
              "data": {
                "skillicon": "https://akmweb.youngjoygame.com/web/svnres/img/mlbb/homepage/100_276900dd1748403fba313aa10476e8f0.png",
                "skillid": 11910
              },
              "id": 110310,
              "sourceId": 2674712
            },
            {
              "_createdAt": 1730960697288,
              "_id": "672c5d399d856a6db37d95d5",
              "_updatedAt": 1758787887535,
              "data": {
                "skillicon": "https://akmweb.youngjoygame.com/web/svnres/img/mlbb/homepage/100_18a74de4a5f949bac5b6d3a6d8a9180b.png",
                "skillid": 11920
              },
              "id": 110309,
              "sourceId": 2674712
            }
          ],
          "title": "LANING COMBOS"
        },
        "dynamic": null,
        "id": 2695069,
        "linkId": [
          2684183
        ],
        "sort": 0,
        "updatedAt": 1713373398175,
        "updatedUser": "rubickguo"
      }
    ],
    "total": 2
  },
  "message": "OK",
  "traceID": null
}