{
  "code": 0,
  "message": "OK",
  "data": {
    "records": [
      {
        "_id": "65f2e27efd1bb8e47d25df19",
        "caption": "008卡琳娜",
        "configId": 144237,
        "createdAt": 1710416510836,
        "createdUser": "nickjin",
        "data": {
          "_object": 2667538,
          "head": "https://akmweb.youngjoygame.com/web/svnres/img/mlbb/community/100_c5a10fb1fb590ae51d1c7118f3937c14.png",
          "head_big": "https://akmweb.youngjoygame.com/web/svnres/file/mlbb/homepage/100_37b5cfef887a7afc63dfaf7b6dfd65c4.jpg",
          "hero": {
            "_createdAt": 1724837697935,
            "_id": "66ceef41af5771f18c50098d",
            "_updatedAt": 1758787900299,
            "data": {
              "abilityshow": [
                "50",
                "70",
                "10",
                "40"
              ],
              "difficulty": "40",
              "head": "https://akmweb.youngjoygame.com/web/svnres/img/mlbb/homepage/100_f49394186dc0e55d545da8377be83280.png",
              "heroid": 8,
              "heroskilllist": [
                {
                  "skilllist": [
                    {
                      "skillcd&cost": "",
                      "skilldesc": "Karina's third consecutive attack on the same enemy deals extra <font color=\"ffe63c\">True Damage</font> equal to 100 plus 5<font color=\"62f8fe\"> (+2.5% Total Magic Power)</font>% of their lost HP (up to 2000 <font color=\"ffe63c\">True Damage</font> against creeps).\n\nIf the target is an enemy hero, the cooldowns of Karina's non-Ultimate skills are reduced by 1.5s.",
                      "skillicon": "https://akmweb.youngjoygame.com/web/svnres/img/mlbb/homepage/100_fb37b0cbc5e9952ec756e3f58c5df22f.png",
                      "skillid": 840,
                      "skillname": "Shadow Combo",
                      "skilltag": [
                        {
                          "tagid": 62,
                          "tagname": "Buff",
                          "tagrgb": "79,156,184"
                        },
                        {
                          "tagid": 33,
                          "tagname": "Damage",
                          "tagrgb": "199,121,85"
                        }
                      ],
                      "skillvideo": ""
                    },
                    {
                      "skillcd&cost": "CD: 7   Mana Cost: 50",
                      "skilldesc": "Karina enters the <font color=\"a6aafb\">Dance of Blades</font> state for 3.5s, during which she gains 45% extra Movement Speed, blocks all incoming Basic Attacks, and reflects 100<font color=\"62f8fe\"> (+30% Total Magic Power)</font> <font color=\"7f62fe\">Magic Damage</font> back to the attacker (the damage reflection effect has a cooldown of 0.4s).\n\nKarina's next Basic Attack within the duration deals 150<font color=\"62f8fe\"> (+55% Total Magic Power)</font> <font color=\"7f62fe\">Magic Damage</font>, slows the target by 45% for 1s, and is guaranteed to Crit. Casting the enhanced Basic Attack or <font color=\"a6aafb\">Shadow Assault</font> ends the <font color=\"a6aafb\">Dance of Blades</font> state early.",
                      "skillicon": "https://akmweb.youngjoygame.com/web/svnres/img/mlbb/homepage/100_94328c502082dd096eb4be3d95655b07.png",
                      "skillid": 810,
                      "skillname": "Dance of Blades",
                      "skilltag": [
                        {
                          "tagid": 62,
                          "tagname": "Buff",
                          "tagrgb": "79,156,184"
                        },
                        {
                          "tagid": 61,
                          "tagname": "Speed Up",
                          "tagrgb": "79,156,184"
                        }
                      ],
                      "skillvideo": ""
                    },
                    {
                      "skillcd&cost": "CD: 6   Mana Cost: 60",
                      "skilldesc": "Karina launches a spinning slash, dealing 375<font color=\"62f8fe\"> (+125% Total Magic Power)</font> <font color=\"7f62fe\">Magic Damage</font> to nearby enemies.",
                      "skillicon": "https://akmweb.youngjoygame.com/web/svnres/img/mlbb/homepage/100_da228e14f0756e84580cb08ede6a1283.png",
                      "skillid": 820,
                      "skillname": "Dance of Death",
                      "skilltag": [
                        {
                          "tagid": 32,
                          "tagname": "AOE",
                          "tagrgb": "199,121,85"
                        }
                      ],
                      "skillvideo": ""
                    },
                    {
                      "skillcd&cost": "CD: 34   Mana Cost: 100",
                      "skilldesc": "Karina dashes to the target enemy hero, dealing them 350<font color=\"62f8fe\"> (+160% Total Magic Power)</font> <font color=\"7f62fe\">Magic Damage</font>, applying a <font color=\"a6aafb\">Shadow Mark</font> to them, and leaving a <font color=\"a6aafb\">Shadowform</font> behind them. The <font color=\"a6aafb\">Shadow Mark</font> and <font color=\"a6aafb\">Shadowform</font> both last 5s. If the enemy dies within the duration, the cooldown of this skill is reset.\n\n<font color=\"a6aafb\">Use Again</font>: Karina dashes back to the <font color=\"a6aafb\">Shadowform</font>'s location, dealing 150<font color=\"62f8fe\"> (+50% Total Magic Power)</font> <font color=\"7f62fe\">Magic Damage</font> to enemies along the way.",
                      "skillicon": "https://akmweb.youngjoygame.com/web/svnres/img/mlbb/homepage/100_889d1d71cef50ed1121ee68b5097954e.png",
                      "skillid": 830,
                      "skillname": "Shadow Assault",
                      "skilltag": [
                        {
                          "tagid": 31,
                          "tagname": "Burst",
                          "tagrgb": "199,121,85"
                        },
                        {
                          "tagid": 81,
                          "tagname": "Mobility",
                          "tagrgb": "162,105,198"
                        }
                      ],
                      "skillvideo": ""
                    }
                  ],
                  "skilllistid": "81"
                }
              ],
              "heroskin": null,
              "name": "Karina",
              "painting": "https://akmweb.youngjoygame.com/web/svnres/img/mlbb/homepage/100_44a9d295baa79bf949fe562ba1b15f2e.png",
              "recommendlevel": [
                "3",
                "2",
                "1"
              ],
              "recommendlevellabel": "3-2-1",
              "recommendmasterplan": [],
              "roadsort": [
                {
                  "_id": "668541caaa8e7f6ec4703d8a",
                  "caption": "打野",
                  "configId": 144237,
                  "createdAt": 1720009162509,
                  "createdUser": "nickjin",
                  "data": {
                    "_object": 2732073,
                    "road_sort_icon": "https://akmweb.youngjoygame.com/web/gms/image/de611167c7310681135f0b4198137bfa.svg",
                    "road_sort_id": "4",
                    "road_sort_title": "Jungle"
                  },
                  "dynamic": null,
                  "id": 2732080,
                  "linkId": [
                    2732073
                  ],
                  "sort": 0,
                  "updatedAt": 1723022951463,
                  "updatedUser": "nickjin"
                },
                ""
              ],
              "roadsorticon1": "https://akmweb.youngjoygame.com/web/svnres/img/mlbb/homepage/100_741d46ff696f02305139a2d817e67e75.png",
              "roadsorticon2": "",
              "roadsortlabel": [
                "Jungle",
                ""
              ],
              "smallmap": "https://akmweb.youngjoygame.com/web/svnres/img/mlbb/homepage_2_1_18/100_4685e0fb17e2fabaf9cb23f8db8fa262.png",
              "sorticon1": "https://akmweb.youngjoygame.com/web/svnres/img/mlbb/homepage/100_933dce3f6078bc4eeaa97caaaa81875f.png",
              "sorticon2": "",
              "sortid": [
                {
                  "_id": "6698bffd613093b976b4a970",
                  "caption": "3刺客",
                  "configId": 144237,
                  "createdAt": 1721286653803,
                  "createdUser": "nickjin",
                  "data": {
                    "_object": 2740651,
                    "sort_icon": "https://akmweb.youngjoygame.com/web/gms/image/d0b8b65a47fc43dc7bb2bac447072fd2.png",
                    "sort_id": "3",
                    "sort_title": "assassin"
                  },
                  "dynamic": null,
                  "id": 2740661,
                  "linkId": [
                    2740651
                  ],
                  "sort": 0,
                  "updatedAt": 1723023131050,
                  "updatedUser": "nickjin"
                },
                ""
              ],
              "sortlabel": [
                "Assassin",
                ""
              ],
              "speciality": [
                "Finisher",
                "Magic Damage"
              ],
              "squarehead": "https://akmweb.youngjoygame.com/web/svnres/file/mlbb/homepage/100_e0e319c392191e1c089270ce257b9af8.jpg",
              "squareheadbig": "https://akmweb.youngjoygame.com/web/svnres/file/mlbb/homepage/100_37b5cfef887a7afc63dfaf7b6dfd65c4.jpg",
              "story": "Killer from the Dark Elf tribe who is fighting to rescue her sister Selena.",
              "tale": ""
            },
            "id": 100381,
            "sourceId": 2756563
          },
          "hero_id": 8,
          "relation": {
            "assist": {
              "desc": "Karina works well with heroes who can pull enemies together, such as Tigreal and Faramis, since her Ultimate and 2nd Skill also hits anyone near her main target, setting them up to be chain killed by her Ultimate.",
              "target_hero": [
                {
                  "data": {
                    "head": "https://akmweb.youngjoygame.com/web/svnres/img/mlbb/homepage/100_8b30576754be1a4f8bebd09df8d6bec7.png"
                  }
                },
                {
                  "data": {
                    "head": "https://akmweb.youngjoygame.com/web/svnres/img/mlbb/homepage/100_04e575d648d7f7ac1174f4369595c3a2.png"
                  }
                },
                0
              ],
              "target_hero_id": [
                6,
                76,
                0
              ]
            },
            "strong": {
              "desc": "Karina counters Marksmen that lack mobility, such as Layla and Hanabi, since her 1st Skill can neutralize their Basic Attacks and they can't escape her high mobility and burst damage.\n",
              "target_hero": [
                {
                  "data": {
                    "head": "https://akmweb.youngjoygame.com/web/svnres/img/mlbb/homepage/100_b2b38e9406ea0de0b866db7674feea0f.png"
                  }
                },
                {
                  "data": {
                    "head": "https://akmweb.youngjoygame.com/web/svnres/img/mlbb/homepage/100_8a9c1966feb34e85d7bdcc1ed01ffb5d.png"
                  }
                },
                0
              ],
              "target_hero_id": [
                18,
                60,
                0
              ]
            },
            "weak": {
              "desc": "Karina is countered by Tanky heroes with CC abilities, like Akai and Khufra because they can tank her damage, and protect their allies from her.",
              "target_hero": [
                {
                  "data": {
                    "head": "https://akmweb.youngjoygame.com/web/svnres/img/mlbb/homepage/100_28f223447f0174336ff0922d364d81d3.png"
                  }
                },
                {
                  "data": {
                    "head": "https://akmweb.youngjoygame.com/web/svnres/img/mlbb/homepage/100_2fe99f4001211d18b3d2b95d0d3dc395.png"
                  }
                },
                0
              ],
              "target_hero_id": [
                9,
                78,
                0
              ]
            }
          },
          "url": "https://play.mobilelegends.com/lore/hero/Karina"
        },
        "dynamic": null,
        "id": 2678744,
        "linkId": [
          2667538
        ],
        "sort": 0,
        "updatedAt": 1726805440128,
        "updatedUser": "nickjin"
      }
    ],
    "total": 1
  }
}